odoo9_addon_project_department-9.0.1.0.0.99.dev7-py3.8-nspkg.pth
odoo_addons/project_department/LICENSE
odoo_addons/project_department/README.rst
odoo_addons/project_department/__init__.py
odoo_addons/project_department/__openerp__.py
odoo_addons/project_department/i18n/ar.po
odoo_addons/project_department/i18n/ca.po
odoo_addons/project_department/i18n/de.po
odoo_addons/project_department/i18n/el.po
odoo_addons/project_department/i18n/es.po
odoo_addons/project_department/i18n/es_CR.po
odoo_addons/project_department/i18n/es_MX.po
odoo_addons/project_department/i18n/es_VE.po
odoo_addons/project_department/i18n/fi.po
odoo_addons/project_department/i18n/fr.po
odoo_addons/project_department/i18n/gl.po
odoo_addons/project_department/i18n/hr.po
odoo_addons/project_department/i18n/hr_HR.po
odoo_addons/project_department/i18n/hu.po
odoo_addons/project_department/i18n/it.po
odoo_addons/project_department/i18n/ja.po
odoo_addons/project_department/i18n/lt.po
odoo_addons/project_department/i18n/lv.po
odoo_addons/project_department/i18n/mk.po
odoo_addons/project_department/i18n/mn.po
odoo_addons/project_department/i18n/nb.po
odoo_addons/project_department/i18n/nb_NO.po
odoo_addons/project_department/i18n/nl.po
odoo_addons/project_department/i18n/pl.po
odoo_addons/project_department/i18n/project_department.pot
odoo_addons/project_department/i18n/pt.po
odoo_addons/project_department/i18n/pt_BR.po
odoo_addons/project_department/i18n/pt_PT.po
odoo_addons/project_department/i18n/ro.po
odoo_addons/project_department/i18n/sl.po
odoo_addons/project_department/i18n/sv.po
odoo_addons/project_department/i18n/tr.po
odoo_addons/project_department/i18n/uk.po
odoo_addons/project_department/i18n/zh_CN.po
odoo_addons/project_department/models/__init__.py
odoo_addons/project_department/models/project.py
odoo_addons/project_department/static/description/icon.png
odoo_addons/project_department/views/project.xml
odoo9_addon_project_department-9.0.1.0.0.99.dev7.dist-info/METADATA
odoo9_addon_project_department-9.0.1.0.0.99.dev7.dist-info/WHEEL
odoo9_addon_project_department-9.0.1.0.0.99.dev7.dist-info/namespace_packages.txt
odoo9_addon_project_department-9.0.1.0.0.99.dev7.dist-info/top_level.txt
odoo9_addon_project_department-9.0.1.0.0.99.dev7.dist-info/RECORD
