Metadata-Version: 2.1
Name: odoo9-addon-project-department
Version: 9.0.1.0.0.99.dev7
Summary: Project Department Categorization
Home-page: http://camptocamp.com
Author: Camptocamp, Daniel Reis,Odoo Community Association (OCA)
Author-email: support@odoo-community.org
License: AGPL-3
Platform: UNKNOWN
Classifier: Programming Language :: Python
Classifier: Framework :: Odoo
Classifier: Framework :: Odoo :: 9.0
Classifier: License :: OSI Approved :: GNU Affero General Public License v3
Requires-Python: ~=2.7
Requires-Dist: odoo9-addon-analytic-base-department
Requires-Dist: odoo (<9.1a,>=9.0a)
